egpy/__init__.py
egpy/eg/__init__.py
egpy/eg/interp/__init__.py
egpy/eg/interp/events_pb2.py
egpy/eg/interp/events_pb2.pyi
egpy/envx/__init__.py
egpy/metrics/__init__.py
egpy/metrics/eg.interp.events_pb2_grpc.py
egpy/metrics/eg_interp_events_pb2_grpc.py
egpy-0.1.1725882192000.dist-info/METADATA
egpy-0.1.1725882192000.dist-info/WHEEL
egpy-0.1.1725882192000.dist-info/top_level.txt
egpy-0.1.1725882192000.dist-info/RECORD
